odoo/addons/stock_picking_batch_planner/README.rst
odoo/addons/stock_picking_batch_planner/__init__.py
odoo/addons/stock_picking_batch_planner/__manifest__.py
odoo/addons/stock_picking_batch_planner/hooks.py
odoo/addons/stock_picking_batch_planner/i18n/es.po
odoo/addons/stock_picking_batch_planner/i18n/it.po
odoo/addons/stock_picking_batch_planner/i18n/stock_picking_batch_planner.pot
odoo/addons/stock_picking_batch_planner/models/__init__.py
odoo/addons/stock_picking_batch_planner/models/stock_picking_batch.py
odoo/addons/stock_picking_batch_planner/models/stock_picking_type.py
odoo/addons/stock_picking_batch_planner/readme/CONFIGURE.md
odoo/addons/stock_picking_batch_planner/readme/CONTEXT.md
odoo/addons/stock_picking_batch_planner/readme/CONTRIBUTORS.md
odoo/addons/stock_picking_batch_planner/readme/DESCRIPTION.md
odoo/addons/stock_picking_batch_planner/readme/USAGE.md
odoo/addons/stock_picking_batch_planner/static/description/icon.png
odoo/addons/stock_picking_batch_planner/static/description/index.html
odoo/addons/stock_picking_batch_planner/tests/__init__.py
odoo/addons/stock_picking_batch_planner/tests/test_stock_picking_batch_planner.py
odoo/addons/stock_picking_batch_planner/views/stock_picking_batch_views.xml
odoo/addons/stock_picking_batch_planner/views/stock_picking_type_views.xml
odoo_addon_stock_picking_batch_planner-18.0.1.0.1.2.dist-info/METADATA
odoo_addon_stock_picking_batch_planner-18.0.1.0.1.2.dist-info/WHEEL
odoo_addon_stock_picking_batch_planner-18.0.1.0.1.2.dist-info/top_level.txt
odoo_addon_stock_picking_batch_planner-18.0.1.0.1.2.dist-info/RECORD
